.gitignore
MANIFEST.in
README.md
setup.py
kevlar/__init__.py
kevlar/checks.py
kevlar/context.py
kevlar/formats.py
kevlar/log.py
kevlar/version.py
kevlar.egg-info/PKG-INFO
kevlar.egg-info/SOURCES.txt
kevlar.egg-info/dependency_links.txt
kevlar.egg-info/not-zip-safe
kevlar.egg-info/requires.txt
kevlar.egg-info/top_level.txt