Metadata-Version: 1.1
Name: kevlar
Version: 0.0.1
Summary: Kevlar will be something cool
Home-page: https://github.com/mattlong/kevlar
Author: Matt Long
Author-email: matt@mattlong.org
License: MIT
Download-URL: https://github.com/mattlong/kevlar/tarball/0.0.1
Platform: UNKNOWN
